[
	{ "PeakcLabel": "PeakCoolingLoad","PeakhLabel": "PeakHeatingLoad",
        "Location": "ADMIN",
        "Climate File": "MAX",
        "DIS": "32",
        "UnmetHoursHeating": "0","UnmetHoursCooling": "155",
        "UH Compliance": "155",
        "PeakHeatingLoad": "3988641",
        "PeakCoolingLoad": "2568606",
        "EUI": "70"
    },
	{ "PeakcLabel": "PeakCoolingLoad","PeakhLabel": "PeakHeatingLoad",
        "Location": "LEARNING 1",
        "Climate File": "MAX",
        "DIS": "36",
        "UnmetHoursHeating": "0","UnmetHoursCooling": "155",
        "UH Compliance": "155",
        "PeakHeatingLoad": "3988641",
        "PeakCoolingLoad": "2568606",
        "EUI": "70"
    },
	{ "PeakcLabel": "PeakCoolingLoad","PeakhLabel": "PeakHeatingLoad",
        "Location": "LEARNING 2",
        "Climate File": "MAX",
        "DIS": "26",
        "UnmetHoursHeating": "0","UnmetHoursCooling": "155",
        "UH Compliance": "155",
        "PeakHeatingLoad": "3988641",
        "PeakCoolingLoad": "2568606",
        "EUI": "70"
    },
	{ "PeakcLabel": "PeakCoolingLoad","PeakhLabel": "PeakHeatingLoad",
        "Location": "PERFORMANCE",
        "Climate File": "MAX",
		"DIS": "25",
        "UnmetHoursHeating": "0","UnmetHoursCooling": "155",
        "UH Compliance": "155",
        "PeakHeatingLoad": "3988641",
        "PeakCoolingLoad": "2568606",
        "EUI": "70"
    },
	{ "PeakcLabel": "PeakCoolingLoad","PeakhLabel": "PeakHeatingLoad",
        "Location": "LEARNING 4",
        "Climate File": "MAX",
        "DIS": "28",
        "UnmetHoursHeating": "0","UnmetHoursCooling": "155",
        "UH Compliance": "155",
        "PeakHeatingLoad": "3988641",
        "PeakCoolingLoad": "2568606",
        "EUI": "70"
    },
	{ "PeakcLabel": "PeakCoolingLoad","PeakhLabel": "PeakHeatingLoad",
        "Location": "LEARNING 3",
        "Climate File": "MAX",
        "DIS": "30",
        "UnmetHoursHeating": "0","UnmetHoursCooling": "155",
        "UH Compliance": "155",
        "PeakHeatingLoad": "3988641",
        "PeakCoolingLoad": "2568606",
        "EUI": "70"
    },
	{ "PeakcLabel": "PeakCoolingLoad","PeakhLabel": "PeakHeatingLoad",
        "Location": "FOOD PREP",
        "Climate File": "MAX",
        "DIS": "35",
        "UnmetHoursHeating": "0","UnmetHoursCooling": "155",
        "UH Compliance": "155",
        "PeakHeatingLoad": "3988641",
        "PeakCoolingLoad": "2568606",
        "EUI": "70"
    },
	{ "PeakcLabel": "PeakCoolingLoad","PeakhLabel": "PeakHeatingLoad",
        "Location": "GYM",
        "Climate File": "MAX",
        "DIS": "30",
        "UnmetHoursHeating": "0","UnmetHoursCooling": "155",
        "UH Compliance": "155",
        "PeakHeatingLoad": "3988641",
        "PeakCoolingLoad": "2568606",
        "EUI": "70"
    }]