[
{ "PeakcLabel": "PeakCoolingLoad","PeakhLabel": "PeakHeatingLoad",
        "Location": "5C",
        "Climate File": "doeCWEC_ILR",
        "FLOOR 1": "11",
        "Mech": "14",
        "FLOOR 2": "12",
        "AUDITORIUM": "12",
        "GYM": "9",
        "KITCHEN CAFETERIA": "51",
        "UnmetHoursHeating": "42","UnmetHoursCooling": "10",
        "UH Compliance": "61",
        "PeakHeatingLoad": "3827630",
        "PeakCoolingLoad": "727729",
        "EUI": "aaa"
    },
    { "PeakcLabel": "PeakCoolingLoad","PeakhLabel": "PeakHeatingLoad",
        "Location": "5C",
        "Climate File": "TMY3WA_ILR",
        "FLOOR 1": "10",
        "Mech": "12",
        "FLOOR 2": "12",
        "AUDITORIUM": "11",
        "GYM": "9",
        "KITCHEN CAFETERIA": "47",
        "UnmetHoursHeating": "42","UnmetHoursCooling": "16",
        "UH Compliance": "63",
        "PeakHeatingLoad": "3827630",
        "PeakCoolingLoad": "727729",
        "EUI": "aaa"
    },
    { "PeakcLabel": "PeakCoolingLoad","PeakhLabel": "PeakHeatingLoad",
        "Location": "5C",
        "Climate File": "TMY7WA_ILR",
        "FLOOR 1": "11",
        "Mech": "14",
        "FLOOR 2": "12",
        "AUDITORIUM": "12",
        "GYM": "9",
        "KITCHEN CAFETERIA": "9",
        "UnmetHoursHeating": "42","UnmetHoursCooling": "114",
        "UH Compliance": "123",
        "PeakHeatingLoad": "3827630",
        "PeakCoolingLoad": "727729",
        "EUI": "aaa"
    },
    { "PeakcLabel": "PeakCoolingLoad","PeakhLabel": "PeakHeatingLoad",
        "Location": "5C",
        "Climate File": "TMY15WA_ILR",
        "FLOOR 1": "11",
        "Mech": "13",
        "FLOOR 2": "12",
        "AUDITORIUM": "11",
        "GYM": "9",
        "KITCHEN CAFETERIA": "37",
        "UnmetHoursHeating": "42","UnmetHoursCooling": "24",
        "UH Compliance": "61",
        "PeakHeatingLoad": "3827630",
        "PeakCoolingLoad": "727729",
        "EUI": "aaa"
    },
    { "PeakcLabel": "PeakCoolingLoad","PeakhLabel": "PeakHeatingLoad",
        "Location": "5C",
        "Climate File": "MAX_ILR",
        "FLOOR 1": "10",
        "Mech": "12",
        "FLOOR 2": "12",
        "AUDITORIUM": "11",
        "GYM": "9",
        "KITCHEN CAFETERIA": "20",
        "UnmetHoursHeating": "42","UnmetHoursCooling": "25",
        "UH Compliance": "45",
        "PeakHeatingLoad": "3827630",
        "PeakCoolingLoad": "727729",
        "EUI": "aaa"
    },
    { "PeakcLabel": "PeakCoolingLoad","PeakhLabel": "PeakHeatingLoad",
        "Location": "5C",
        "Climate File": "MIN_ILR",
        "FLOOR 1": "15",
        "Mech": "20",
        "FLOOR 2": "15",
        "AUDITORIUM": "15",
        "GYM": "11",
        "KITCHEN CAFETERIA": "0",
        "UnmetHoursHeating": "42","UnmetHoursCooling": "324",
        "UH Compliance": "324",
        "PeakHeatingLoad": "3827630",
        "PeakCoolingLoad": "727729",
        "EUI": "aaa"
    },
    { "PeakcLabel": "PeakCoolingLoad","PeakhLabel": "PeakHeatingLoad",
        "Location": "5C",
        "Climate File": "doeCWEC_ILR",
        "FLOOR 1": "11",
        "Mech": "14",
        "FLOOR 2": "12",
        "AUDITORIUM": "12",
        "GYM": "9",
        "KITCHEN CAFETERIA": "371",
        "UnmetHoursHeating": "42","UnmetHoursCooling": "0",
        "UH Compliance": "371",
        "PeakHeatingLoad": "3827630",
        "PeakCoolingLoad": "727729",
        "EUI": "aaa"
    },
    { "PeakcLabel": "PeakCoolingLoad","PeakhLabel": "PeakHeatingLoad",
        "Location": "5C",
        "Climate File": "CWEC_ILR",
        "FLOOR 1": "#N/A",
        "Mech": "#N/A",
        "FLOOR 2": "#N/A",
        "AUDITORIUM": "#N/A",
        "GYM": "#N/A",
        "KITCHEN CAFETERIA": "538",
        "UnmetHoursHeating": "42","UnmetHoursCooling": "63",
        "UH Compliance": "601",
        "PeakHeatingLoad": "5063981",
        "PeakCoolingLoad": "1230803",
        "EUI": "aaa"
    }

]