[
 {"PeakcLabel": "PeakCoolingLoad","PeakhLabel": "PeakHeatingLoad",
        "Location": "FLOOR 1",
        "Climate File": "MAX",
        "DIS": "88",
        "Unmet Hours (Heating)": "1",
        "UnmetHoursCooling": "23",
        "UH Compliance": "24",
        "PeakHeatingLoad": "4088501",
        "PeakCoolingLoad": "1694811",
        "EUI": "aaa"
    },
 {"PeakcLabel": "PeakCoolingLoad","PeakhLabel": "PeakHeatingLoad",
        "Location": "MECH",
        "Climate File": "MAX",
        "DIS": "25",
        "Unmet Hours (Heating)": "1",
        "UnmetHoursCooling": "23",
        "UH Compliance": "24",
        "PeakHeatingLoad": "4088501",
        "PeakCoolingLoad": "1694811",
        "EUI": "aaa"
    },
 {"PeakcLabel": "PeakCoolingLoad","PeakhLabel": "PeakHeatingLoad",
        "Location": "FLOOR 2",
        "Climate File": "MAX",
        "DIS": "90",
        "Unmet Hours (Heating)": "1",
        "UnmetHoursCooling": "23",
        "UH Compliance": "24",
        "PeakHeatingLoad": "4088501",
        "PeakCoolingLoad": "1694811",
        "EUI": "aaa"
    },
 {"PeakcLabel": "PeakCoolingLoad","PeakhLabel": "PeakHeatingLoad",
        "Location": "AUDITORIUM",
        "Climate File": "MAX",
        "DIS": "20",
        "Unmet Hours (Heating)": "1",
        "UnmetHoursCooling": "23",
        "UH Compliance": "24",
        "PeakHeatingLoad": "4088501",
        "PeakCoolingLoad": "1694811",
        "EUI": "aaa"
    },
 {"PeakcLabel": "PeakCoolingLoad","PeakhLabel": "PeakHeatingLoad",
        "Location": "GYM",
        "Climate File": "MAX",
        "DIS": "14",
        "Unmet Hours (Heating)": "1",
        "UnmetHoursCooling": "23",
        "UH Compliance": "24",
        "PeakHeatingLoad": "4088501",
        "PeakCoolingLoad": "1694811",
        "EUI": "aaa"
    },
 {"PeakcLabel": "PeakCoolingLoad","PeakhLabel": "PeakHeatingLoad",
        "Location": "KITCHEN",
        "Climate File": "MAX",
        "DIS": "22",
        "Unmet Hours (Heating)": "1",
        "UnmetHoursCooling": "23",
        "UH Compliance": "24",
        "PeakHeatingLoad": "4088501",
        "PeakCoolingLoad": "1694811",
        "EUI": "aaa"
    }

]