[
{
        "Climate Zone": "4C",
        "Climate File": "TMY3 ILR",
        "FLOOR 1": "11",
        "Mech": "13",
        "FLOOR 2": "12",
        "AUDITORIUM": "12",
        "GYM": "9",
        "KITCHEN CAFETERIA": "58",
        "Unmet Hours (Cooling)": "47",
        "UH Compliance": "105",
        "Peak Heating Load": "3717432",
        "Peak Cooling Load": "1320260",
        "EUI": "aaa"
    },
    {
        "Climate Zone": "4C",
        "Climate File": "TMY3WA ILR",
        "FLOOR 1": "10",
        "Mech": "13",
        "FLOOR 2": "12",
        "AUDITORIUM": "11",
        "GYM": "9",
        "KITCHEN CAFETERIA": "54",
        "Unmet Hours (Cooling)": "30",
        "UH Compliance": "84",
        "Peak Heating Load": "3717432",
        "Peak Cooling Load": "1320260",
        "EUI": "aaa"
    },
    {
        "Climate Zone": "4C",
        "Climate File": "TMY7WA ILR",
        "FLOOR 1": "11",
        "Mech": "15",
        "FLOOR 2": "13",
        "AUDITORIUM": "12",
        "GYM": "10",
        "KITCHEN CAFETERIA": "25",
        "Unmet Hours (Cooling)": "143",
        "UH Compliance": "168",
        "Peak Heating Load": "3717432",
        "Peak Cooling Load": "1320260",
        "EUI": "aaa"
    },
    {
        "Climate Zone": "4C",
        "Climate File": "TMY2 ILR",
        "FLOOR 1": "11",
        "Mech": "13",
        "FLOOR 2": "12",
        "AUDITORIUM": "12",
        "GYM": "9",
        "KITCHEN CAFETERIA": "66",
        "Unmet Hours (Cooling)": "166",
        "UH Compliance": "232",
        "Peak Heating Load": "3717432",
        "Peak Cooling Load": "1320260",
        "EUI": "aaa"
    },
    {
        "Climate Zone": "4C",
        "Climate File": "MIN ILR",
        "FLOOR 1": "15",
        "Mech": "21",
        "FLOOR 2": "15",
        "AUDITORIUM": "16",
        "GYM": "11",
        "KITCHEN CAFETERIA": "37",
        "Unmet Hours (Cooling)": "175",
        "UH Compliance": "212",
        "Peak Heating Load": "3717432",
        "Peak Cooling Load": "1320260",
        "EUI": "aaa"
    },
    {
        "Climate Zone": "4C",
        "Climate File": "TMY15WA ILR",
        "FLOOR 1": "11",
        "Mech": "14",
        "FLOOR 2": "13",
        "AUDITORIUM": "12",
        "GYM": "9",
        "KITCHEN CAFETERIA": "0",
        "Unmet Hours (Cooling)": "675",
        "UH Compliance": "675",
        "Peak Heating Load": "3717432",
        "Peak Cooling Load": "1320260",
        "EUI": "aaa"
    },
    {
        "Climate Zone": "4C",
        "Climate File": "MAX ILR",
        "FLOOR 1": "12",
        "Mech": "14",
        "FLOOR 2": "14",
        "AUDITORIUM": "12",
        "GYM": "11",
        "KITCHEN CAFETERIA": "451",
        "Unmet Hours (Cooling)": "0",
        "UH Compliance": "451",
        "Peak Heating Load": "3717432",
        "Peak Cooling Load": "1320260",
        "EUI": "aaa"
    }

]